ws/caldavcheck/__init__.py
ws/caldavcheck/main.py
ws.caldavcheck-1.0.2.dist-info/METADATA
ws.caldavcheck-1.0.2.dist-info/WHEEL
ws.caldavcheck-1.0.2.dist-info/entry_points.txt
ws.caldavcheck-1.0.2.dist-info/RECORD
