Metadata-Version: 2.1
Name: ws.caldavcheck
Version: 1.0.2
Summary: Creates an event in a CalDAV calendar, and checks that it can be read back
Project-URL: Repository, https://github.com/wosc/caldavcheck
Author-email: Wolfgang Schnerring <wosc@wosc.de>
License:  BSD-3-Clause
Requires-Python: >=3.7
Requires-Dist: caldav
Requires-Dist: vobject
Provides-Extra: test
Requires-Dist: pytest; extra == 'test'
Requires-Dist: pytest-cov; extra == 'test'
